[{"data":[{"h":"96.3","t":"5.7","dht":14},{"h":"73.0","t":"8.6","dht":12},{"h":"64.1","t":"8.2","dht":13}],"timestamp":"2017-10-30T09:16:52.583"},{"data":[{"h":"96.3","t":"5.7","dht":14},{"h":73,"t":"8.6","dht":12},{"h":"64.1","t":"8.3","dht":13}],"timestamp":"2017-10-30T09:16:58.194"},{"data":[{"h":"96.3","t":"5.7","dht":14},{"h":"72.6","t":"8.6","dht":12},{"h":"64.0","t":"8.3","dht":13}],"timestamp":"2017-10-30T09:17:02.827"},{"data":[{"h":"96.3","t":"5.7","dht":14},{"h":"72.5","t":"8.6","dht":12},{"h":64,"t":"8.3","dht":13}],"timestamp":"2017-10-30T09:17:08.789"},{"data":[{"h":"96.3","t":"5.7","dht":14},{"h":"71.6","t":"8.6","dht":12},{"h":"63.2","t":"8.3","dht":13}],"timestamp":"2017-10-30T09:17:12.693"},{"data":[{"h":"96.3","t":"5.7","dht":14},{"h":"71.5","t":"8.6","dht":12},{"h":63,"t":"8.3","dht":13}],"timestamp":"2017-10-30T09:17:22.522"},{"data":[{"h":"96.3","t":"5.7","dht":14},{"h":"71.5","t":"8.6","dht":12},{"h":63,"t":"8.3","dht":13}],"timestamp":"2017-10-30T09:17:23.116"},{"data":[{"h":"96.3","t":"5.7","dht":14},{"h":"71.5","t":"8.5","dht":12},{"h":63,"t":"8.2","dht":13}],"timestamp":"2017-10-30T09:17:26.824"},{"data":[{"h":"96.3","t":"5.7","dht":14},{"h":"71.5","t":"8.5","dht":12},{"h":63,"t":"8.2","dht":13}],"timestamp":"2017-10-30T09:17:34.235"},{"data":[{"h":"96.3","t":"5.7","dht":14},{"h":71,"t":"8.5","dht":12},{"h":"62.7","t":"8.2","dht":13}],"timestamp":"2017-10-30T09:17:38.020"},{"data":[{"h":"96.3","t":"5.7","dht":14},{"h":"70.5","t":"8.5","dht":12},{"h":"62.0","t":"8.1","dht":13}],"timestamp":"2017-10-30T09:17:43.235"},{"data":[{"h":"96.1","t":"5.7","dht":14},{"h":"70.5","t":8,"dht":12},{"h":62,"t":"7.8","dht":13}],"timestamp":"2017-10-30T09:24:30.316"},{"data":[{"h":"96.1","t":"5.7","dht":14},{"h":"70.5","t":"8.1","dht":12},{"h":62,"t":"7.8","dht":13}],"timestamp":"2017-10-30T09:24:32.901"},{"data":[{"h":"96.1","t":"5.7","dht":14},{"h":"70.5","t":8,"dht":12},{"h":62,"t":"7.8","dht":13}],"timestamp":"2017-10-30T09:24:37.666"},{"data":[{"h":"96.1","t":"5.7","dht":14},{"h":"70.5","t":8,"dht":12},{"h":62,"t":"7.8","dht":13}],"timestamp":"2017-10-30T09:24:43.334"},{"data":[{"h":"96.1","t":"5.7","dht":14},{"h":"70.5","t":8,"dht":12},{"h":"61.7","t":"7.7","dht":13}],"timestamp":"2017-10-30T09:29:21.753"},{"data":[{"h":"96.1","t":"5.7","dht":14},{"h":"70.4","t":"7.9","dht":12},{"h":"61.7","t":"7.6","dht":13}],"timestamp":"2017-10-30T09:29:24.887"},{"data":[{"h":"96.1","t":"5.7","dht":14},{"h":"70.4","t":"7.9","dht":12},{"h":"61.7","t":"7.6","dht":13}],"timestamp":"2017-10-30T09:29:30.411"},{"data":[{"h":"96.1","t":"5.7","dht":14},{"h":"70.4","t":"7.9","dht":12},{"h":"61.7","t":"7.6","dht":13}],"timestamp":"2017-10-30T09:29:35.279"},{"data":[{"h":"96.1","t":"5.7","dht":14},{"h":"70.5","t":"7.9","dht":12},{"h":"61.7","t":"7.6","dht":13}],"timestamp":"2017-10-30T09:29:44.809"},{"data":[{"h":"96.1","t":"5.7","dht":14},{"h":"70.5","t":"7.9","dht":12},{"h":"61.9","t":"7.6","dht":13}],"timestamp":"2017-10-30T09:29:45.648"},{"data":[{"h":"96.1","t":"5.7","dht":14},{"h":"70.5","t":"7.9","dht":12},{"h":"61.9","t":"7.6","dht":13}],"timestamp":"2017-10-30T09:29:49.877"},{"data":[{"h":"96.1","t":"5.7","dht":14},{"h":"70.5","t":"7.9","dht":12},{"h":"61.9","t":"7.6","dht":13}],"timestamp":"2017-10-30T09:29:55.791"},{"data":[{"h":"96.0","t":"5.7","dht":14},{"h":"70.4","t":"7.9","dht":12},{"h":"61.7","t":"7.6","dht":13}],"timestamp":"2017-10-30T09:30:01.437"},{"data":[{"h":"96.0","t":"5.7","dht":14},{"h":"70.4","t":"7.9","dht":12},{"h":"61.9","t":"7.7","dht":13}],"timestamp":"2017-10-30T09:30:04.905"},{"data":[{"h":"96.0","t":"5.7","dht":14},{"h":"70.5","t":"7.9","dht":12},{"h":"61.7","t":"7.6","dht":13}],"timestamp":"2017-10-30T09:30:14.878"},{"data":[{"h":"96.0","t":"5.7","dht":14},{"h":"70.4","t":"7.9","dht":12},{"h":"61.7","t":"7.6","dht":13}],"timestamp":"2017-10-30T09:30:15.742"},{"data":[{"h":"96.0","t":"5.7","dht":14},{"h":"70.4","t":"7.9","dht":12},{"h":"61.7","t":"7.6","dht":13}],"timestamp":"2017-10-30T09:30:20.165"},{"data":[{"h":"96.0","t":"5.7","dht":14},{"h":"70.4","t":"7.9","dht":12},{"h":"61.7","t":"7.6","dht":13}],"timestamp":"2017-10-30T09:30:27.422"},{"data":[{"h":"96.0","t":"5.7","dht":14},{"h":"70.4","t":"7.9","dht":12},{"h":"61.7","t":"7.6","dht":13}],"timestamp":"2017-10-30T09:30:29.902"}]